sphinx_simrofy_theme/__init__.py
sphinx_simrofy_theme/layout.html
sphinx_simrofy_theme/socialmedia.html
sphinx_simrofy_theme/theme.conf
sphinx_simrofy_theme/static/simrofy.css_t
sphinx_simrofy_theme/static/icon/github.png
sphinx_simrofy_theme/static/icon/social-500px.png
sphinx_simrofy_theme/static/icon/social-aboutme.png
sphinx_simrofy_theme/static/icon/social-amazon.png
sphinx_simrofy_theme/static/icon/social-android.png
sphinx_simrofy_theme/static/icon/social-angellist.png
sphinx_simrofy_theme/static/icon/social-apple.png
sphinx_simrofy_theme/static/icon/social-behance.png
sphinx_simrofy_theme/static/icon/social-bilibili.png
sphinx_simrofy_theme/static/icon/social-bookmate.png
sphinx_simrofy_theme/static/icon/social-buffer.png
sphinx_simrofy_theme/static/icon/social-codepen.png
sphinx_simrofy_theme/static/icon/social-coub.png
sphinx_simrofy_theme/static/icon/social-delicious.png
sphinx_simrofy_theme/static/icon/social-devianart.png
sphinx_simrofy_theme/static/icon/social-digg.png
sphinx_simrofy_theme/static/icon/social-dribble.png
sphinx_simrofy_theme/static/icon/social-dropbox.png
sphinx_simrofy_theme/static/icon/social-ello.png
sphinx_simrofy_theme/static/icon/social-envato.png
sphinx_simrofy_theme/static/icon/social-etsy-short.png
sphinx_simrofy_theme/static/icon/social-etsy.png
sphinx_simrofy_theme/static/icon/social-evernote.png
sphinx_simrofy_theme/static/icon/social-facebook.png
sphinx_simrofy_theme/static/icon/social-favorite.png
sphinx_simrofy_theme/static/icon/social-flikr.png
sphinx_simrofy_theme/static/icon/social-foursquare.png
sphinx_simrofy_theme/static/icon/social-github.png
sphinx_simrofy_theme/static/icon/social-google+.png
sphinx_simrofy_theme/static/icon/social-googledrive.png
sphinx_simrofy_theme/static/icon/social-googleplay.png
sphinx_simrofy_theme/static/icon/social-habrahabr.png
sphinx_simrofy_theme/static/icon/social-instagram.png
sphinx_simrofy_theme/static/icon/social-jsfiddle.png
sphinx_simrofy_theme-0.4.1.dist-info/LICENSE
sphinx_simrofy_theme-0.4.1.dist-info/METADATA
sphinx_simrofy_theme-0.4.1.dist-info/WHEEL
sphinx_simrofy_theme-0.4.1.dist-info/entry_points.txt
sphinx_simrofy_theme-0.4.1.dist-info/top_level.txt
sphinx_simrofy_theme-0.4.1.dist-info/RECORD
