Metadata-Version: 2.1
Name: sphinx-simrofy-theme
Version: 0.4.1
Summary: A sphinx theme for creating personal portfolio website.
Home-page: https://github.com/wklchris/sphinx-simrofy-theme
Author: wklchris
Author-email: wklchris@hotmail.com
License: UNKNOWN
Platform: UNKNOWN
Classifier: Programming Language :: Python :: 3
Classifier: License :: OSI Approved :: MIT License
Classifier: Operating System :: OS Independent
Requires-Python: >=3.6
License-File: LICENSE
Requires-Dist: Sphinx (>=4.0.0)
Requires-Dist: nbsphinx (>=0.8.4)
Requires-Dist: sphinxcontrib-bibtex (>=2.0.0)
Requires-Dist: sphinx-intl (>=2.0.0)
